{
	"credit": "Made with Blockbench",
	"texture_size": [48, 48],
	"textures": {
		"0": "item/chicken_raw",
		"particle": "item/chicken_raw"
	},
	"elements": [
		{
			"from": [1, 0, 3],
			"to": [15, 8, 13],
			"faces": {
				"north": {"uv": [3.33333, 13.33333, 8, 16], "texture": "#0"},
				"east": {"uv": [0, 13.33333, 3.33333, 16], "texture": "#0"},
				"south": {"uv": [3.33333, 13.33333, 8, 16], "texture": "#0"},
				"west": {"uv": [0, 13.33333, 3.33333, 16], "texture": "#0"},
				"up": {"uv": [8, 13.33333, 3.33333, 10], "texture": "#0"},
				"down": {"uv": [8, 10, 3.33333, 13.33333], "texture": "#0"}
			}
		},
		{
			"from": [8, 1, 1],
			"to": [15, 5, 3],
			"rotation": {"angle": 0, "axis": "y", "origin": [11.5, 6, 2]},
			"faces": {
				"north": {"uv": [9.66667, 11.33333, 12, 12.66667], "texture": "#0"},
				"east": {"uv": [9, 11.33333, 9.66667, 12.66667], "texture": "#0"},
				"south": {"uv": [9.66667, 11.33333, 12, 12.66667], "texture": "#0"},
				"west": {"uv": [9, 11.33333, 9.66667, 12.66667], "texture": "#0"},
				"up": {"uv": [12, 11.33333, 9.66667, 10.66667], "texture": "#0"},
				"down": {"uv": [12, 10.66667, 9.66667, 11.33333], "texture": "#0"}
			}
		},
		{
			"from": [7.5, 3.75, 1.025],
			"to": [10.5, 7.75, 3.025],
			"rotation": {"angle": 22.5, "axis": "z", "origin": [9.5, 7, 2]},
			"faces": {
				"north": {"uv": [11.66667, 8, 12.66667, 9.33333], "texture": "#0"},
				"east": {"uv": [11, 8, 11.66667, 9.33333], "texture": "#0"},
				"south": {"uv": [11.66667, 8, 12.66667, 9.33333], "texture": "#0"},
				"west": {"uv": [11, 8, 11.66667, 9.33333], "texture": "#0"},
				"up": {"uv": [12.66667, 8, 11.66667, 7.33333], "texture": "#0"},
				"down": {"uv": [12.66667, 7.33333, 11.66667, 8], "texture": "#0"}
			}
		},
		{
			"from": [-3.75, 3.75, 5],
			"to": [1.25, 6.75, 11],
			"rotation": {"angle": 22.5, "axis": "z", "origin": [-1.5, 6.5, 8]},
			"faces": {
				"north": {"uv": [8.66667, 5.33333, 10.33333, 6.33333], "texture": "#0"},
				"east": {"uv": [6.66667, 5.33333, 8.66667, 6.33333], "texture": "#0"},
				"south": {"uv": [8.66667, 5.33333, 10.33333, 6.33333], "texture": "#0"},
				"west": {"uv": [6.66667, 5.33333, 8.66667, 6.33333], "texture": "#0"},
				"up": {"uv": [10.33333, 5.33333, 8.66667, 3.33333], "texture": "#0"},
				"down": {"uv": [10.33333, 3.33333, 8.66667, 5.33333], "texture": "#0"}
			}
		},
		{
			"from": [0.44517, 4.04511, -1],
			"to": [8.44517, 9.04511, 3],
			"rotation": {"angle": -45, "axis": "z", "origin": [0.33868, 6.89157, 8]},
			"faces": {
				"north": {"uv": [3.33333, 2.66667, 6, 4.33333], "texture": "#0"},
				"east": {"uv": [2, 2.66667, 3.33333, 4.33333], "texture": "#0"},
				"south": {"uv": [3.33333, 2.66667, 6, 4.33333], "texture": "#0"},
				"west": {"uv": [2, 2.66667, 3.33333, 4.33333], "texture": "#0"},
				"up": {"uv": [6, 2.66667, 3.33333, 1.33333], "texture": "#0"},
				"down": {"uv": [6, 1.33333, 3.33333, 2.66667], "texture": "#0"}
			}
		},
		{
			"from": [-2.55483, 5.04511, -0.5],
			"to": [0.44517, 8.04511, 2.5],
			"rotation": {"angle": -45, "axis": "z", "origin": [0.33868, 6.89157, 8]},
			"faces": {
				"north": {"uv": [9, 8.33333, 10, 9.33333], "texture": "#0"},
				"east": {"uv": [9, 8.33333, 10, 9.33333], "texture": "#0"},
				"south": {"uv": [9, 8.33333, 10, 9.33333], "texture": "#0"},
				"west": {"uv": [9, 8.33333, 10, 9.33333], "texture": "#0"},
				"up": {"uv": [10, 9.33333, 9, 8.33333], "texture": "#0"},
				"down": {"uv": [10, 8.33333, 9, 9.33333], "texture": "#0"}
			}
		},
		{
			"from": [-1.91273, 9.31806, 0],
			"to": [0.08727, 12.31806, 2],
			"rotation": {"angle": 22.5, "axis": "z", "origin": [0.33868, 6.89157, 8]},
			"faces": {
				"north": {"uv": [14, 11.33333, 14.66667, 12.33333], "texture": "#0"},
				"east": {"uv": [14, 11.33333, 14.66667, 12.33333], "texture": "#0"},
				"south": {"uv": [14, 11.33333, 14.66667, 12.33333], "texture": "#0"},
				"west": {"uv": [14, 11.33333, 14.66667, 12.33333], "texture": "#0"},
				"up": {"uv": [14.66667, 11.33333, 14, 10.66667], "texture": "#0"},
				"down": {"uv": [14.66667, 10.66667, 14, 11.33333], "texture": "#0"}
			}
		},
		{
			"from": [-2.55483, 5.04511, 13.5],
			"to": [0.44517, 8.04511, 16.5],
			"rotation": {"angle": -45, "axis": "z", "origin": [0.33868, 6.89157, 8]},
			"faces": {
				"north": {"uv": [10, 8.33333, 9, 9.33333], "texture": "#0"},
				"east": {"uv": [10, 8.33333, 9, 9.33333], "texture": "#0"},
				"south": {"uv": [10, 8.33333, 9, 9.33333], "texture": "#0"},
				"west": {"uv": [10, 8.33333, 9, 9.33333], "texture": "#0"},
				"up": {"uv": [10, 8.33333, 9, 9.33333], "texture": "#0"},
				"down": {"uv": [10, 9.33333, 9, 8.33333], "texture": "#0"}
			}
		},
		{
			"from": [-1.91273, 9.31806, 14],
			"to": [0.08727, 12.31806, 16],
			"rotation": {"angle": 22.5, "axis": "z", "origin": [0.33868, 6.89157, 8]},
			"faces": {
				"north": {"uv": [14.66667, 11.33333, 14, 12.33333], "texture": "#0"},
				"east": {"uv": [14.66667, 11.33333, 14, 12.33333], "texture": "#0"},
				"south": {"uv": [14.66667, 11.33333, 14, 12.33333], "texture": "#0"},
				"west": {"uv": [14.66667, 11.33333, 14, 12.33333], "texture": "#0"},
				"up": {"uv": [14.66667, 10.66667, 14, 11.33333], "texture": "#0"},
				"down": {"uv": [14.66667, 11.33333, 14, 10.66667], "texture": "#0"}
			}
		},
		{
			"from": [0.44517, 4.04511, 13],
			"to": [8.44517, 9.04511, 17],
			"rotation": {"angle": -45, "axis": "z", "origin": [0.33868, 6.89157, 8]},
			"faces": {
				"north": {"uv": [6, 2.66667, 3.33333, 4.33333], "texture": "#0"},
				"east": {"uv": [3.33333, 2.66667, 2, 4.33333], "texture": "#0"},
				"south": {"uv": [6, 2.66667, 3.33333, 4.33333], "texture": "#0"},
				"west": {"uv": [3.33333, 2.66667, 2, 4.33333], "texture": "#0"},
				"up": {"uv": [6, 1.33333, 3.33333, 2.66667], "texture": "#0"},
				"down": {"uv": [6, 2.66667, 3.33333, 1.33333], "texture": "#0"}
			}
		},
		{
			"from": [8, 1, 13],
			"to": [15, 5, 15],
			"rotation": {"angle": 0, "axis": "y", "origin": [11.5, 6, 14]},
			"faces": {
				"north": {"uv": [12, 11.33333, 9.66667, 12.66667], "texture": "#0"},
				"east": {"uv": [9.66667, 11.33333, 9, 12.66667], "texture": "#0"},
				"south": {"uv": [12, 11.33333, 9.66667, 12.66667], "texture": "#0"},
				"west": {"uv": [9.66667, 11.33333, 9, 12.66667], "texture": "#0"},
				"up": {"uv": [12, 10.66667, 9.66667, 11.33333], "texture": "#0"},
				"down": {"uv": [12, 11.33333, 9.66667, 10.66667], "texture": "#0"}
			}
		},
		{
			"from": [7.5, 3.75, 12.975],
			"to": [10.5, 7.75, 14.975],
			"rotation": {"angle": 22.5, "axis": "z", "origin": [9.5, 7, 14]},
			"faces": {
				"north": {"uv": [12.66667, 8, 11.66667, 9.33333], "texture": "#0"},
				"east": {"uv": [11.66667, 8, 11, 9.33333], "texture": "#0"},
				"south": {"uv": [12.66667, 8, 11.66667, 9.33333], "texture": "#0"},
				"west": {"uv": [11.66667, 8, 11, 9.33333], "texture": "#0"},
				"up": {"uv": [12.66667, 7.33333, 11.66667, 8], "texture": "#0"},
				"down": {"uv": [12.66667, 8, 11.66667, 7.33333], "texture": "#0"}
			}
		},
		{
			"from": [14, -1, 4],
			"to": [19, 5, 12],
			"rotation": {"angle": -22.5, "axis": "z", "origin": [19.5, 5, 8]},
			"faces": {
				"north": {"uv": [2.66667, 7.66667, 4.33333, 9.66667], "texture": "#0"},
				"east": {"uv": [4.33333, 7.66667, 7, 9.66667], "texture": "#0"},
				"south": {"uv": [2.66667, 7.66667, 4.33333, 9.66667], "texture": "#0"},
				"west": {"uv": [4.33333, 7.66667, 7, 9.66667], "texture": "#0"},
				"up": {"uv": [4.33333, 7.66667, 2.66667, 5], "texture": "#0"},
				"down": {"uv": [4.33333, 5, 2.66667, 7.66667], "texture": "#0"}
			}
		}
	],
	"gui_light": "front",
	"display": {
		"thirdperson_righthand": {
			"rotation": [30, -69.54, 16.26],
			"translation": [0, 2.5, 2],
			"scale": [0.4, 0.4, 0.4]
		},
		"thirdperson_lefthand": {
			"rotation": [38, 111, -22],
			"translation": [0, 2.5, 2],
			"scale": [0.4, 0.4, 0.4]
		},
		"firstperson_righthand": {
			"rotation": [-8.08, 32.07, 87.53],
			"translation": [2.63, 3.45, -5.87],
			"scale": [0.7, 0.7, 0.7]
		},
		"firstperson_lefthand": {
			"rotation": [-172.69, -21.21, 97.19],
			"translation": [2.63, 3.45, -5.87],
			"scale": [0.7, 0.7, 0.7]
		},
		"ground": {
			"translation": [0, 2, 0],
			"scale": [0.5, 0.5, 0.5]
		},
		"gui": {
			"rotation": [30.14, 33.9, 21.92],
			"translation": [0, 1.5, 0],
			"scale": [0.5, 0.5, 0.5]
		},
		"head": {
			"rotation": [0, 180, 0],
			"translation": [0, 13, 7]
		},
		"fixed": {
			"rotation": [0, 180, 0]
		}
	}
}