{
	"credit": "Made with Blockbench",
	"texture_size": [32, 32],
	"textures": {
		"0": "item/cod",
		"particle": "item/cod"
	},
	"elements": [
		{
			"from": [21.76, 6.01, 5.01],
			"to": [30.74, 14.99, 10.99],
			"rotation": {"angle": -45, "axis": "z", "origin": [27.25, 10.5, 8]},
			"faces": {
				"north": {"uv": [4.83721, 13.76744, 6.51163, 15.44186], "texture": "#0"},
				"east": {"uv": [6.51163, 13.76744, 7.62791, 15.44186], "texture": "#0"},
				"south": {"uv": [6.51163, 13.76744, 4.83721, 15.44186], "texture": "#0"},
				"west": {"uv": [7.62791, 13.76744, 8.74419, 15.44186], "texture": "#0"},
				"up": {"uv": [6.51163, 13.76744, 4.83721, 12.65116], "texture": "#0"},
				"down": {"uv": [8.18605, 12.65116, 6.51163, 13.76744], "texture": "#0"}
			}
		},
		{
			"from": [26.99487, 6.04513, 5.02],
			"to": [31.95487, 8.00513, 10.98],
			"rotation": {"angle": 0, "axis": "y", "origin": [29.72487, 8.02513, 8]},
			"faces": {
				"north": {"uv": [2.4186, 6.88372, 3.34884, 7.25581], "texture": "#0"},
				"east": {"uv": [3.34884, 6.88372, 4.46512, 7.25581], "texture": "#0"},
				"south": {"uv": [2.4186, 6.88372, 3.34884, 7.25581], "texture": "#0"},
				"west": {"uv": [3.34884, 6.88372, 4.46512, 7.25581], "texture": "#0"},
				"up": {"uv": [3.34884, 6.88372, 2.4186, 5.76744], "texture": "#0"},
				"down": {"uv": [4.27907, 5.76744, 3.34884, 6.88372], "texture": "#0"}
			}
		},
		{
			"from": [26.88132, 11.13132, 4.01],
			"to": [29.86132, 14.11132, 4.99],
			"rotation": {"angle": 22.5, "axis": "z", "origin": [28.37132, 12.62132, 4.5]},
			"faces": {
				"north": {"uv": [6.13953, 6.69767, 6.69767, 7.25581], "texture": "#0"},
				"east": {"uv": [5.95349, 6.69767, 6.13953, 7.25581], "texture": "#0"},
				"south": {"uv": [6.13953, 6.69767, 6.69767, 7.25581], "texture": "#0"},
				"west": {"uv": [5.95349, 6.69767, 6.13953, 7.25581], "texture": "#0"},
				"up": {"uv": [6.69767, 6.69767, 6.13953, 6.51163], "texture": "#0"},
				"down": {"uv": [6.69767, 6.51163, 6.13953, 6.69767], "texture": "#0"}
			}
		},
		{
			"from": [26.88132, 11.13132, 11.01],
			"to": [29.86132, 14.11132, 11.99],
			"rotation": {"angle": 22.5, "axis": "z", "origin": [28.37132, 12.62132, 11.5]},
			"faces": {
				"north": {"uv": [6.13953, 6.7093, 6.69767, 7.26744], "texture": "#0"},
				"east": {"uv": [5.95349, 6.7093, 6.13953, 7.26744], "texture": "#0"},
				"south": {"uv": [6.13953, 6.7093, 6.69767, 7.26744], "texture": "#0"},
				"west": {"uv": [5.95349, 6.7093, 6.13953, 7.26744], "texture": "#0"},
				"up": {"uv": [6.69767, 6.7093, 6.13953, 6.52326], "texture": "#0"},
				"down": {"uv": [6.69767, 6.52326, 6.13953, 6.7093], "texture": "#0"}
			}
		},
		{
			"from": [6.75, 5, 5],
			"to": [25.75, 16, 11],
			"rotation": {"angle": 0, "axis": "y", "origin": [21.25, 10.5, 8]},
			"faces": {
				"north": {"uv": [1.48837, 8.93023, 5.02326, 10.97674], "texture": "#0"},
				"east": {"uv": [0.37209, 8.93023, 1.48837, 10.97674], "texture": "#0"},
				"south": {"uv": [5.02326, 8.93023, 1.48837, 10.97674], "texture": "#0"},
				"west": {"uv": [0.37209, 8.93023, 1.48837, 10.97674], "texture": "#0"},
				"up": {"uv": [5.02326, 8.93023, 1.48837, 7.81395], "texture": "#0"},
				"down": {"uv": [5.02326, 10.97674, 1.48837, 12.09302], "texture": "#0"}
			}
		},
		{
			"from": [12.75, 6, 1.5],
			"to": [21.75, 15, 1.5],
			"rotation": {"angle": -22.5, "axis": "y", "origin": [12.25, 10.5, 1.5]},
			"faces": {
				"north": {"uv": [7.25581, 5.39535, 8.93023, 7.06977], "texture": "#0"},
				"east": {"uv": [0, 0, 0, 1.67442], "texture": "#0"},
				"south": {"uv": [7.25581, 5.39535, 8.93023, 7.06977], "texture": "#0"},
				"west": {"uv": [8.93023, 5.39535, 8.93023, 7.06977], "texture": "#0"},
				"up": {"uv": [1.67442, 0, 0, 0], "texture": "#0"},
				"down": {"uv": [3.34884, 0, 1.67442, 0], "texture": "#0"}
			}
		},
		{
			"from": [12.75, 6, 14.5],
			"to": [21.75, 15, 14.5],
			"rotation": {"angle": 22.5, "axis": "y", "origin": [12.25, 10.5, 14.5]},
			"faces": {
				"north": {"uv": [7.25581, 5.39535, 8.93023, 7.06977], "texture": "#0"},
				"east": {"uv": [0, 0, 0, 1.67442], "texture": "#0"},
				"south": {"uv": [8.93023, 5.39535, 7.25581, 7.06977], "texture": "#0"},
				"west": {"uv": [8.93023, 5.39535, 8.93023, 7.06977], "texture": "#0"},
				"up": {"uv": [1.67442, 0, 0, 0], "texture": "#0"},
				"down": {"uv": [3.34884, 0, 1.67442, 0], "texture": "#0"}
			}
		},
		{
			"from": [-3.25, 6, 5],
			"to": [6.75, 15, 11],
			"rotation": {"angle": 0, "axis": "y", "origin": [8.25, 10.5, 8]},
			"faces": {
				"north": {"uv": [5.95349, 9.48837, 7.81395, 11.16279], "texture": "#0"},
				"east": {"uv": [7.81395, 9.48837, 8.93023, 11.16279], "texture": "#0"},
				"south": {"uv": [7.81395, 9.48837, 5.95349, 11.16279], "texture": "#0"},
				"west": {"uv": [7.81395, 9.48837, 8.93023, 11.16279], "texture": "#0"},
				"up": {"uv": [7.81395, 9.48837, 5.95349, 8.37209], "texture": "#0"},
				"down": {"uv": [9.67442, 8.37209, 7.81395, 9.48837], "texture": "#0"}
			}
		},
		{
			"from": [-11.25, 7, 5],
			"to": [-3.25, 14, 11],
			"rotation": {"angle": 0, "axis": "y", "origin": [0.25, 10.5, 8]},
			"faces": {
				"north": {"uv": [10.7907, 11.34884, 12.27907, 12.65116], "texture": "#0"},
				"east": {"uv": [9.67442, 11.34884, 10.7907, 12.65116], "texture": "#0"},
				"south": {"uv": [12.27907, 11.34884, 10.7907, 12.65116], "texture": "#0"},
				"west": {"uv": [9.67442, 11.34884, 10.7907, 12.65116], "texture": "#0"},
				"up": {"uv": [11.16279, 11.34884, 9.67442, 10.23256], "texture": "#0"},
				"down": {"uv": [12.65116, 10.23256, 11.16279, 11.34884], "texture": "#0"}
			}
		},
		{
			"from": [-16, 3, 8],
			"to": [-6, 18, 8],
			"rotation": {"angle": 0, "axis": "y", "origin": [-4.75, 10.5, 11]},
			"faces": {
				"north": {"uv": [10.97674, 6.88372, 12.83721, 9.67442], "texture": "#0"},
				"east": {"uv": [10.97674, 6.32558, 10.97674, 9.11628], "texture": "#0"},
				"south": {"uv": [12.83721, 6.88372, 10.97674, 9.67442], "texture": "#0"},
				"west": {"uv": [12.65116, 6.32558, 12.65116, 9.11628], "texture": "#0"},
				"up": {"uv": [12.83721, 6.32558, 10.97674, 6.32558], "texture": "#0"},
				"down": {"uv": [14.51163, 6.32558, 12.65116, 6.32558], "texture": "#0"}
			}
		},
		{
			"from": [-6.25, -2, 8],
			"to": [26.75, 27, 8],
			"rotation": {"angle": 0, "axis": "y", "origin": [25.25, 10.5, 11]},
			"faces": {
				"north": {"uv": [0, 0, 6.13953, 5.39535], "texture": "#0"},
				"east": {"uv": [0, 0, 0, 5.39535], "texture": "#0"},
				"south": {"uv": [6.13953, 0, 0, 5.39535], "texture": "#0"},
				"west": {"uv": [6.13953, 0, 6.13953, 5.39535], "texture": "#0"},
				"up": {"uv": [6.13953, 0, 0, 0], "texture": "#0"},
				"down": {"uv": [12.27907, 0, 6.13953, 0], "texture": "#0"}
			}
		}
	],
	"gui_light": "front",
	"display": {
		"thirdperson_righthand": {
			"rotation": [44.56, 88.7, 36.01],
			"translation": [0.25, -2.5, 0],
			"scale": [0.35, 0.35, 0.35]
		},
		"thirdperson_lefthand": {
			"rotation": [127.31, -88.7, 36.01],
			"translation": [0.25, -2.5, 0],
			"scale": [0.35, 0.35, 0.35]
		},
		"firstperson_righthand": {
			"rotation": [175.1, 63.23, -164.25],
			"translation": [6.13, -4.3, -3.87],
			"scale": [0.68, 0.68, 0.68]
		},
		"firstperson_lefthand": {
			"rotation": [12.18, -74.46, -1.76],
			"translation": [6.13, -4.3, -3.87],
			"scale": [0.68, 0.68, 0.68]
		},
		"ground": {
			"translation": [0, 2, 0],
			"scale": [0.5, 0.5, 0.5]
		},
		"gui": {
			"rotation": [-159.75, -31.64, -151.33],
			"translation": [-0.75, -1, 0],
			"scale": [0.35, 0.35, 0.35]
		},
		"head": {
			"rotation": [0, 180, 0],
			"translation": [0, 13, 7]
		},
		"fixed": {
			"rotation": [0, 180, 0]
		}
	}
}